kxmc_mcp_server_file_system_win/__init__.py
kxmc_mcp_server_file_system_win/__main__.py
kxmc_mcp_server_file_system_win/main.py
kxmc_mcp_file_system_win-0.1.3.dist-info/METADATA
kxmc_mcp_file_system_win-0.1.3.dist-info/WHEEL
kxmc_mcp_file_system_win-0.1.3.dist-info/top_level.txt
kxmc_mcp_file_system_win-0.1.3.dist-info/RECORD
